MusicStream/Metadata.py
MusicStream/Playlist.py
MusicStream/Spotify.py
MusicStream/YoutubeMusic.py
MusicStream/__init__.py
MusicStream/cli.py
musicstream-0.0.1.dist-info/LICENSE
musicstream-0.0.1.dist-info/METADATA
musicstream-0.0.1.dist-info/WHEEL
musicstream-0.0.1.dist-info/top_level.txt
musicstream-0.0.1.dist-info/RECORD
